pathmap/__init__.py
pathmap/pathmap.py
pathmap/tree.py
pathmap/utils.py
pathmap-0.1.5.dist-info/DESCRIPTION.rst
pathmap-0.1.5.dist-info/METADATA
pathmap-0.1.5.dist-info/RECORD
pathmap-0.1.5.dist-info/WHEEL
pathmap-0.1.5.dist-info/metadata.json
pathmap-0.1.5.dist-info/top_level.txt
